odoo8_addon_hr_timesheet_holiday-8.0.1.1.0.99.dev10-nspkg.pth
odoo_addons/hr_timesheet_holiday/README.rst
odoo_addons/hr_timesheet_holiday/__init__.py
odoo_addons/hr_timesheet_holiday/__openerp__.py
odoo_addons/hr_timesheet_holiday/i18n/es.po
odoo_addons/hr_timesheet_holiday/i18n/fr.po
odoo_addons/hr_timesheet_holiday/i18n/hr_timesheet_holiday.pot
odoo_addons/hr_timesheet_holiday/i18n/sl.po
odoo_addons/hr_timesheet_holiday/models/__init__.py
odoo_addons/hr_timesheet_holiday/models/analytic_account.py
odoo_addons/hr_timesheet_holiday/models/analytic_line.py
odoo_addons/hr_timesheet_holiday/models/company.py
odoo_addons/hr_timesheet_holiday/models/hr_analytic_timesheet.py
odoo_addons/hr_timesheet_holiday/models/hr_holidays.py
odoo_addons/hr_timesheet_holiday/models/hr_holidays_status.py
odoo_addons/hr_timesheet_holiday/models/hr_timesheet_sheet.py
odoo_addons/hr_timesheet_holiday/static/description/icon.png
odoo_addons/hr_timesheet_holiday/tests/__init__.py
odoo_addons/hr_timesheet_holiday/tests/test_all.py
odoo_addons/hr_timesheet_holiday/views/company_view.xml
odoo_addons/hr_timesheet_holiday/views/hr_holidays_view.xml
odoo8_addon_hr_timesheet_holiday-8.0.1.1.0.99.dev10.dist-info/METADATA
odoo8_addon_hr_timesheet_holiday-8.0.1.1.0.99.dev10.dist-info/WHEEL
odoo8_addon_hr_timesheet_holiday-8.0.1.1.0.99.dev10.dist-info/namespace_packages.txt
odoo8_addon_hr_timesheet_holiday-8.0.1.1.0.99.dev10.dist-info/top_level.txt
odoo8_addon_hr_timesheet_holiday-8.0.1.1.0.99.dev10.dist-info/RECORD
