Metadata-Version: 2.1
Name: odoo8-addon-hr-timesheet-holiday
Version: 8.0.1.1.0.99.dev10
Summary: When holidays are granted, add lines to the analytic account that is linked to the Leave Type
Home-page: http://sunflowerweb.nl
Author: Sunflower IT, Therp BV, Odoo Community Association (OCA)
Author-email: support@odoo-community.org
License: AGPL-3
Platform: UNKNOWN
Classifier: Programming Language :: Python
Classifier: Framework :: Odoo
Classifier: License :: OSI Approved :: GNU Affero General Public License v3
Requires-Python: ~=2.7
Requires-Dist: odoo (<9.0a,>=8.0a)
